{"allDetail": {"E": {"foe1Switch": false, "foe2Switch": false, "foe1Format": 0, "foe2Format": 0, "foe1Compare": 0, "foe2Compare": 0, "buff": 4, "foe1Num": "1", "foe2Num": "1", "foe1Deal": 0, "foe2Deal": 0, "spy": false, "spyDeal": 0, "nightFight": false, "isFormat": false, "format": 0}, "L": {"foe1Switch": false, "foe2Switch": false, "foe1Format": 0, "foe2Format": 0, "foe1Compare": 0, "foe2Compare": 0, "buff": 1, "foe1Num": "1", "foe2Num": "1", "foe1Deal": 0, "foe2Deal": 0, "spy": false, "spyDeal": 0, "nightFight": false, "isFormat": false, "format": 0}}, "map": "801", "name": "8-1\u6253\u635eL", "point": "BEHL", "format": 1, "spyFail": 0, "skip": false, "skipDeal": 0, "hmChange": false, "qmChange": false, "qtChange": true, "reward": false, "nightFight": false, "resource": false}